LICENSE
README.md
setup.py
src/dynasigml/__init__.py
src/dynasigml/dynasig_df.py
src/dynasigml/dynasig_ml_model.py
src/dynasigml.egg-info/PKG-INFO
src/dynasigml.egg-info/SOURCES.txt
src/dynasigml.egg-info/dependency_links.txt
src/dynasigml.egg-info/requires.txt
src/dynasigml.egg-info/top_level.txt