Metadata-Version: 2.1
Name: dynasigml
Version: 1.0.7
Summary: DynaSig-ML
Home-page: https://github.com/gregorpatof/dynasigml_package
Author: Olivier Mailhot
License: UNKNOWN
Platform: UNKNOWN
Classifier: Programming Language :: Python :: 3
Classifier: License :: OSI Approved :: MIT License
Classifier: Operating System :: OS Independent
Requires-Python: >=3.6
License-File: LICENSE
